code_scope_mcp/__init__.py
code_scope_mcp/__main__.py
code_scope_mcp/constants.py
code_scope_mcp/project_settings.py
code_scope_mcp/server.py
code_scope_mcp/symbol_finder.py
code_scope_mcp/db/database.py
code_scope_mcp/indexing/__init__.py
code_scope_mcp/indexing/ignore_handler.py
code_scope_mcp/indexing/indexing_logger.py
code_scope_mcp/indexing/languages.py
code_scope_mcp/indexing/models.py
code_scope_mcp/indexing/orchestrator.py
code_scope_mcp/indexing/reader.py
code_scope_mcp/indexing/scanner.py
code_scope_mcp/indexing/timing_utils.py
code_scope_mcp/indexing/writer.py
code_scope_mcp/indexing/relationship_handlers/__init__.py
code_scope_mcp/indexing/relationship_handlers/base_relationship_handler.py
code_scope_mcp/indexing/relationship_handlers/common/base_file_function_call_handler.py
code_scope_mcp/indexing/relationship_handlers/common/base_import_handler.py
code_scope_mcp/indexing/relationship_handlers/common/base_inherits_handler.py
code_scope_mcp/indexing/relationship_handlers/common/base_instantiation_handler.py
code_scope_mcp/indexing/relationship_handlers/common/base_is_instance_of_handler.py
code_scope_mcp/indexing/relationship_handlers/common/base_member_function_call_handler.py
code_scope_mcp/indexing/relationship_handlers/javascript/file_function_call_handler.py
code_scope_mcp/indexing/relationship_handlers/javascript/import_handler.py
code_scope_mcp/indexing/relationship_handlers/javascript/inherits_handler.py
code_scope_mcp/indexing/relationship_handlers/javascript/instantiation_handler.py
code_scope_mcp/indexing/relationship_handlers/javascript/is_instance_of_handler.py
code_scope_mcp/indexing/relationship_handlers/javascript/member_function_call_handler.py
code_scope_mcp/indexing/relationship_handlers/javascript/references_variable_handler.py
code_scope_mcp/indexing/relationship_handlers/php/__init__.py
code_scope_mcp/indexing/relationship_handlers/php/file_function_call_handler.py
code_scope_mcp-0.0.1.dist-info/licenses/LICENSE
code_scope_mcp-0.0.1.dist-info/METADATA
code_scope_mcp-0.0.1.dist-info/WHEEL
code_scope_mcp-0.0.1.dist-info/entry_points.txt
code_scope_mcp-0.0.1.dist-info/top_level.txt
code_scope_mcp-0.0.1.dist-info/RECORD
