Metadata-Version: 2.4
Name: code-scope-mcp
Version: 0.0.1
Summary: Code indexing and analysis tools for LLMs using MCP
Author: marksolly
License-Expression: MIT
Project-URL: Homepage, https://github.com/marksolly/code-scope-mcp
Project-URL: Bug Tracker, https://github.com/marksolly/code-scope-mcp/issues
Requires-Python: >=3.10
License-File: LICENSE
Requires-Dist: mcp>=0.3.0
Requires-Dist: watchdog>=3.0.0
Requires-Dist: tree-sitter==0.21.0
Requires-Dist: tree-sitter-languages==1.10.0
Requires-Dist: pathspec>=0.12.0
Dynamic: license-file
